prompit/__init__.py
prompit/cli.py
prompit/module.py
prompit/utils.py
prompit-0.3.3.dist-info/LICENSE
prompit-0.3.3.dist-info/METADATA
prompit-0.3.3.dist-info/WHEEL
prompit-0.3.3.dist-info/entry_points.txt
prompit-0.3.3.dist-info/top_level.txt
prompit-0.3.3.dist-info/RECORD
