Metadata-Version: 2.1
Name: prompit
Version: 0.3.3
Summary: Prompit
Home-page: https://github.com/oliveirabruno01/prompit
Author: oliveirabruno01
Author-email: brunocabeludo321@gmail.com
License: MIT
Keywords: AI engineering,prompt engineering
Requires-Python: >=3.8.0
License-File: LICENSE
Requires-Dist: pathspec ~=0.12.1
Requires-Dist: pytest ~=8.1.1
Requires-Dist: pytest-cov
Requires-Dist: pathlib ~=1.0.1
